ssp/__init__.py
ssp/api.py
ssp/control.py
ssp/securityplan.py
regscale_python_ssp-0.1.2.dist-info/LICENSE
regscale_python_ssp-0.1.2.dist-info/METADATA
regscale_python_ssp-0.1.2.dist-info/WHEEL
regscale_python_ssp-0.1.2.dist-info/top_level.txt
regscale_python_ssp-0.1.2.dist-info/RECORD
