Metadata-Version: 2.1
Name: regscale-python-ssp
Version: 0.1.2
Summary: Library for interfacing with FedRAMP system security plan templates.
Home-page: https://github.com/regscale/regscale-python-ssp
Author: Elliot DeMatteis
License: MIT License
Keywords: fedramp ssp word
Classifier: Development Status :: 3 - Alpha
Classifier: Programming Language :: Python :: 3
Classifier: License :: OSI Approved :: MIT License
License-File: LICENSE
Requires-Dist: python-docx
